CHANGELOG
COPYRIGHT
INSTALL
LICENSE
MANIFEST.in
README
setup.py
htmlentity2ascii/__init__.py
htmlentity2ascii.egg-info/PKG-INFO
htmlentity2ascii.egg-info/SOURCES.txt
htmlentity2ascii.egg-info/dependency_links.txt
htmlentity2ascii.egg-info/top_level.txt